Metadata-Version: 1.0
Name: pyshort
Version: 1.0
Summary: A simple python package to generate short code via predefined code and size , also you can add extra strings .
Home-page: https://github.com/nishowsan/pyshort/
Author: Adib Mohsin
Author-email: md.nishow@gmail.com
License: MIT
Platform: UNKNOWN
